Metadata-Version: 2.1
Name: eliteapi
Version: 0.3
Summary: eliteapi is a Python wrapper for Elite Creative allowing you to easly interact with the API.
Home-page: https://github.com/KappaOnGit/eliteapi
Author: Kappa
Author-email: f.cappetti.05@gmail.com
License: MIT
Download-URL: https://github.com/FraKappa/eliteapi/archive/v_02.tar.gz
Keywords: eliteapi,elite
Platform: UNKNOWN
Classifier: Development Status :: 3 - Alpha
Classifier: Intended Audience :: Developers
Classifier: Topic :: Software Development :: Build Tools
Classifier: License :: OSI Approved :: MIT License
Classifier: Programming Language :: Python :: 3
